aioresult/__init__.py
aioresult/_aio.py
aioresult/_src.py
aioresult/_version.py
aioresult/_wait.py
aioresult/py.typed
aioresult-1.2.dist-info/LICENSE
aioresult-1.2.dist-info/METADATA
aioresult-1.2.dist-info/WHEEL
aioresult-1.2.dist-info/top_level.txt
aioresult-1.2.dist-info/RECORD
