Metadata-Version: 2.2
Name: aioresult
Version: 1.2
Summary: Capture the result of a Trio or anyio task
Author: Arthur Tacca
License: Boost Software License - Version 1.0 - August 17th, 2003
Project-URL: Repository, https://github.com/arthur-tacca/aioresult
Project-URL: Documentation, https://aioresult.readthedocs.io/en/v1.2/overview.html
Keywords: async,anyio,trio,result,future,nursery,taskgroup
Classifier: Development Status :: 5 - Production/Stable
Classifier: Framework :: AnyIO
Classifier: Framework :: Trio
Classifier: Intended Audience :: Developers
Classifier: License :: OSI Approved :: Boost Software License 1.0 (BSL-1.0)
Classifier: Operating System :: OS Independent
Classifier: Programming Language :: Python :: 3 :: Only
Classifier: Programming Language :: Python :: 3.9
Classifier: Programming Language :: Python :: 3.10
Classifier: Programming Language :: Python :: 3.11
Classifier: Programming Language :: Python :: 3.12
Classifier: Programming Language :: Python :: 3.13
Classifier: Programming Language :: Python :: Implementation :: CPython
Classifier: Programming Language :: Python :: Implementation :: PyPy
Classifier: Topic :: System :: Networking
Requires-Python: >=3.9
License-File: LICENSE
Requires-Dist: sniffio>=1.0.0
Requires-Dist: typing_extensions>=4.1.0
Provides-Extra: docs
Requires-Dist: sphinx>=6.1; extra == "docs"
Requires-Dist: sphinxcontrib-trio; extra == "docs"
Requires-Dist: sphinx_rtd_theme; extra == "docs"
Requires-Dist: trio; extra == "docs"
Requires-Dist: anyio; extra == "docs"
Provides-Extra: tests
Requires-Dist: pytest; extra == "tests"
Requires-Dist: coverage; extra == "tests"
Requires-Dist: trio; extra == "tests"
Requires-Dist: anyio; extra == "tests"
Requires-Dist: exceptiongroup; python_version < "3.11" and extra == "tests"
